<?xml version="1.0" encoding="UTF-8"?>
<flow id="ec545f78-2e6b-454e-9b13-b1958628027b">
  <descriptionCdata><![CDATA[ec545f78-2e6b-454e-9b13-b1958628027b.02735f3f-b09b-4142-9258-1e0a272667f6.transition.description=rowcount \!\= 1
ec545f78-2e6b-454e-9b13-b1958628027b.081838ee-dc0f-416d-b22b-1a25bafd1d72.transition.description=rowcount \=\= 1
ec545f78-2e6b-454e-9b13-b1958628027b.0f649cf7-5267-476f-8ad8-debb624e27ff.description=<pre>Checks if a number or word is equal to another number or word. Word comparison is case-sensitive in alphabetical order.\n\nInputs\:\nvalue1 - The first value.\nvalue2 - The second value.\n\nReturns\:\nvalue1 \=\= value2\n\nResponses\:\nsuccess - The boolean operation was evaluated to true.\nfailure - Something went wrong or the boolean operation returned false.\n</pre>
ec545f78-2e6b-454e-9b13-b1958628027b.13c1ff90-d531-4f9c-be67-45915b51b252.transition.description=automation failure
ec545f78-2e6b-454e-9b13-b1958628027b.6bb5cf0a-81c6-4cfe-9f8f-b8d296e6ef13.transition.description=success
ec545f78-2e6b-454e-9b13-b1958628027b.7a9cfd94-d98f-4d1d-80de-d807ca7b2abf.description=<pre>\nThis operation adds a flow variable to the local context. The variable is available in the current flow and its child flows.\n\nInputs\:\n    keyName - The name of the flow variable to add.\n    myValue - The value to assign to the flow variable.\n\nResults\:\n    returnResult - This is the primary output. It contains the value of "myValue" input field.\n\nResponses\:\n    success - The operation completed as stated in the description.\n\nNote\:\n   If a flow variable with the same name already exists, its value will be overwritten.\n</pre>
ec545f78-2e6b-454e-9b13-b1958628027b.b404aa62-1666-4ba6-add1-b64d6a4af42f.description=<pre>This is an operation that does nothing. It can be used for filtering flow variables by feeding them in as inputs and filtering them on the results tab.\n\nResponses\:\n    success\n    failure\n</pre>
ec545f78-2e6b-454e-9b13-b1958628027b.c52f0def-fbad-4d5c-9d27-5de81e16f913.transition.description=automation failure
ec545f78-2e6b-454e-9b13-b1958628027b.d5138e93-e35d-440d-a46b-8ac729f53540.description=<pre>\nAdds a list of flow variables to the local context. The variables are available in the current flow and its child flows.\n\nInputs\:\n    keyNames - The names of the flow variables to add, separated by "delimiter".\n    myValues - The values to assign to the flow variables, separated by "delimiter".\n    delimiter - The delimiter that separates the key names and the values from the "keyNames" and "myValues" input strings.\n\nResults\:\n    returnResult - This is the primary output. It contains the value of "myValue" input field.\n\nResponses\:\n    success - The operation completed as stated in the description.\n\nNotes\:\n1. If the number of variable names is greater than the number of variable values, the value of each variable will be the value of "myValues" input field.\n2. If the number of variable names is less than the number of variable values, the additional variable values will be discarded.\n</pre>
ec545f78-2e6b-454e-9b13-b1958628027b.e101bf4d-9084-4288-bcf1-49ca6e715ba1.transition.description=success
]]></descriptionCdata>
  <annotation></annotation>
  <name>Determine Update Screens</name>
  <categories/>
  <inputs>
    <staticBinding id="3e0c4c87-0fa5-4bc3-bfa6-42f7c8c603e5">
      <annotation></annotation>
      <assignFromContext>true</assignFromContext>
      <assignToContext>false</assignToContext>
      <inputType>STRING</inputType>
      <isList>false</isList>
      <required>false</required>
      <isPersisted>true</isPersisted>
      <inputSymbol>switchID</inputSymbol>
      <listDelimiter>,</listDelimiter>
      <value></value>
      <record>false</record>
    </staticBinding>
    <staticBinding id="3db9439e-d566-4beb-8626-e856ac74e14b">
      <annotation></annotation>
      <assignFromContext>true</assignFromContext>
      <assignToContext>false</assignToContext>
      <inputType>STRING</inputType>
      <isList>false</isList>
      <required>false</required>
      <isPersisted>true</isPersisted>
      <inputSymbol>day</inputSymbol>
      <listDelimiter>,</listDelimiter>
      <value></value>
      <record>false</record>
    </staticBinding>
  </inputs>
  <possibleResponses>
    <opResponse id="ff626c46-909c-45b4-b2d5-8be88031ba7b">
      <annotation></annotation>
      <name>failure</name>
      <isDefault>false</isDefault>
      <onFailure>true</onFailure>
      <type>ERROR</type>
      <matchRules/>
    </opResponse>
    <opResponse id="ad2be47e-d5b6-478b-b333-0cd6b9d90d95">
      <annotation></annotation>
      <name>success</name>
      <isDefault>true</isDefault>
      <onFailure>false</onFailure>
      <type>RESOLVED</type>
      <matchRules/>
    </opResponse>
  </possibleResponses>
  <availableResultExpressions>
    <expression id="1886e77d-9be7-4aeb-b506-0dd6fc528ee5">
      <annotation></annotation>
      <name>errorMessage</name>
      <fieldName>errorMessage</fieldName>
      <sourceType>RAWRESULT</sourceType>
      <filters/>
    </expression>
    <expression id="47f15993-f45e-4a42-a04d-c9a3be0e3b7f">
      <annotation></annotation>
      <name>failureFlag</name>
      <fieldName>failureFlag</fieldName>
      <sourceType>RAWRESULT</sourceType>
      <filters/>
    </expression>
    <expression id="9161cb79-fbfa-4c1e-8f7d-94c88c35f739">
      <annotation></annotation>
      <name>updateACHCFlag</name>
      <fieldName>updateACHCFlag</fieldName>
      <sourceType>RAWRESULT</sourceType>
      <filters/>
    </expression>
    <expression id="6dbe74f7-0daa-4553-9c66-7cb828798cb9">
      <annotation></annotation>
      <name>updateCCTPFlag</name>
      <fieldName>updateCCTPFlag</fieldName>
      <sourceType>RAWRESULT</sourceType>
      <filters/>
    </expression>
    <expression id="641d9478-d4b6-4374-a4b5-8dfa98814b9d">
      <annotation></annotation>
      <name>updateCS90Flag</name>
      <fieldName>updateCS90Flag</fieldName>
      <sourceType>RAWRESULT</sourceType>
      <filters/>
    </expression>
    <expression id="da94abf4-6953-475c-bed8-ef0fd227898b">
      <annotation></annotation>
      <name>updateDATEFlag</name>
      <fieldName>updateDATEFlag</fieldName>
      <sourceType>RAWRESULT</sourceType>
      <filters/>
    </expression>
    <expression id="995fd2f0-3e7d-433d-8817-8ab1c5e15716">
      <annotation></annotation>
      <name>updateDRDBFlag</name>
      <fieldName>updateDRDBFlag</fieldName>
      <sourceType>RAWRESULT</sourceType>
      <filters/>
    </expression>
    <expression id="c28f78d5-f340-4fab-8255-61305da80bb8">
      <annotation></annotation>
      <name>updateFACTFlag</name>
      <fieldName>updateFACTFlag</fieldName>
      <sourceType>RAWRESULT</sourceType>
      <filters/>
    </expression>
    <expression id="5287de9f-d290-4c5b-bf31-e7af24a5d472">
      <annotation></annotation>
      <name>updateFADSFlag</name>
      <fieldName>updateFADSFlag</fieldName>
      <sourceType>RAWRESULT</sourceType>
      <filters/>
    </expression>
    <expression id="8dbda2d9-e7aa-4866-ac69-7d2ce575dca4">
      <annotation></annotation>
      <name>updateLBRDFlag</name>
      <fieldName>updateLBRDFlag</fieldName>
      <sourceType>RAWRESULT</sourceType>
      <filters/>
    </expression>
    <expression id="757c1b41-1cc9-4960-909f-4c5fd49b7fe9">
      <annotation></annotation>
      <name>updateLNS4Flag</name>
      <fieldName>updateLNS4Flag</fieldName>
      <sourceType>RAWRESULT</sourceType>
      <filters/>
    </expression>
    <expression id="e4991479-b85c-4c8b-8e9d-8d0a513fd060">
      <annotation></annotation>
      <name>updatePDSWFlag</name>
      <fieldName>updatePDSWFlag</fieldName>
      <sourceType>RAWRESULT</sourceType>
      <filters/>
    </expression>
    <expression id="fa736455-e1f2-47d4-86f4-c81fdb7a3ad2">
      <annotation></annotation>
      <name>updatePRCDFlag</name>
      <fieldName>updatePRCDFlag</fieldName>
      <sourceType>RAWRESULT</sourceType>
      <filters/>
    </expression>
    <expression id="12f109e5-f749-40ba-b1c3-89c433d82a9d">
      <annotation></annotation>
      <name>updateTENTFlag</name>
      <fieldName>updateTENTFlag</fieldName>
      <sourceType>RAWRESULT</sourceType>
      <filters/>
    </expression>
    <expression id="2bce1589-6774-4da7-a3e3-3f9771e83e9d">
      <annotation></annotation>
      <name>updateVCHGFlag</name>
      <fieldName>updateVCHGFlag</fieldName>
      <sourceType>RAWRESULT</sourceType>
      <filters/>
    </expression>
    <expression id="8d099a75-51e1-4d8d-9496-7bf473fad574">
      <annotation></annotation>
      <name>updateVMGDFlag</name>
      <fieldName>updateVMGDFlag</fieldName>
      <sourceType>RAWRESULT</sourceType>
      <filters/>
    </expression>
    <expression id="d49d12af-7a15-4425-8dc4-56960bb0612b">
      <annotation></annotation>
      <name>updateVRMIFlag</name>
      <fieldName>updateVRMIFlag</fieldName>
      <sourceType>RAWRESULT</sourceType>
      <filters/>
    </expression>
  </availableResultExpressions>
  <resultExpression id="6943a61a-dbda-44d1-81b2-4b38b00dfb5f">
    <annotation></annotation>
    <name>FailureMessage</name>
    <fieldName>FailureMessage</fieldName>
    <sourceType>RAWRESULT</sourceType>
    <filters/>
  </resultExpression>
  <iconSpec id="3a28e175-0482-46c2-bdb6-9898b927c18a">
    <baseIcon>flow.png</baseIcon>
    <basePath>System</basePath>
    <readOnly>false</readOnly>
    <layers/>
  </iconSpec>
  <callouts/>
  <checkPointFlow>true</checkPointFlow>
  <compatibleRuntimeContext>false</compatibleRuntimeContext>
  <historyCheckPointFlow>true</historyCheckPointFlow>
  <steps>
    <step id="f995eb94-e0ee-4cc2-a2d9-9dc32206b56d">
      <annotation></annotation>
      <name>Determine Update Screens</name>
      <bounds>
        <x>30.0</x>
        <y>260.0</y>
      </bounds>
      <layer>-1</layer>
      <hideInbound>false</hideInbound>
      <iconSpec id="53de2855-c151-4d6c-a5de-687131a456dd">
        <baseIcon>flow.png</baseIcon>
        <basePath>System</basePath>
        <readOnly>false</readOnly>
        <layers/>
      </iconSpec>
      <addResultToRunContext>false</addResultToRunContext>
      <isCriticalStep>false</isCriticalStep>
      <isNonBlocking>false</isNonBlocking>
      <isParallelStep>false</isParallelStep>
      <isSingleResponse>false</isSingleResponse>
      <recordInHistory>false</recordInHistory>
      <recordRawOutput>true</recordRawOutput>
      <recordPrimaryOutput>true</recordPrimaryOutput>
      <checkPointStep>true</checkPointStep>
      <historyCheckPointStep>true</historyCheckPointStep>
      <scriptResultStep>false</scriptResultStep>
      <userPrompt></userPrompt>
      <bindings>
        <staticBinding id="445eb262-f841-43f5-b25c-f94beef6348d">
          <annotation></annotation>
          <fromContextKey>WBC/Usecases/ProductSwitch_V1.00/AutomationTable_WBC_SD_PRODUCT_SWITCH_MATRIX</fromContextKey>
          <assignFromContext>true</assignFromContext>
          <assignToContext>false</assignToContext>
          <inputType>STRING</inputType>
          <isList>false</isList>
          <required>false</required>
          <isPersisted>true</isPersisted>
          <inputSymbol>tableName</inputSymbol>
          <listDelimiter>,</listDelimiter>
          <value></value>
          <record>false</record>
        </staticBinding>
        <staticBinding id="b679a5bd-0bee-4254-99de-cef6ded3deb3">
          <annotation></annotation>
          <assignFromContext>false</assignFromContext>
          <assignToContext>false</assignToContext>
          <inputType>STRING</inputType>
          <isList>false</isList>
          <required>false</required>
          <isPersisted>true</isPersisted>
          <inputSymbol>query</inputSymbol>
          <listDelimiter>,</listDelimiter>
          <value>SELECT
PSW_UPDATE_PDSW as updatePDSW,
PSW_UPDATE_FACT as updateFACT,
PSW_UPDATE_CS90 as updateCS90,
PSW_UPDATE_LBRD as updateLBRD,
PSW_UPDATE_CCTP as updateCCTP,
PSW_UPDATE_VCHG as updateVCHG,
PSW_UPDATE_LNS4 as updateLNS4,
PSW_UPDATE_VRMI as updateVRMI,
PSW_UPDATE_DATE as updateDATE,
PSW_UPDATE_FADS as updateFADS,
PSW_UPDATE_TENT as updateTENT,
PSW_UPDATE_PRCD as updatePRCD,
PSW_UPDATE_DRDB as updateDRDB,
PSW_UPDATE_VMGD as updateVMGD,
PSW_UPDATE_ACHC as updateACHC
FROM ${tableName}
where 
PSW_SW_ID = &apos;${switchID}&apos; 
AND PSW_SW_DAY = &apos;${day}&apos;</value>
          <record>false</record>
        </staticBinding>
        <staticBinding id="95a61897-804f-4ef4-9546-24b26f984bbd">
          <annotation></annotation>
          <assignFromContext>false</assignFromContext>
          <assignToContext>true</assignToContext>
          <inputType>STRING</inputType>
          <isList>false</isList>
          <required>false</required>
          <isPersisted>true</isPersisted>
          <inputSymbol>columnDelimiter</inputSymbol>
          <listDelimiter>,</listDelimiter>
          <value>;</value>
          <record>false</record>
        </staticBinding>
        <staticBinding id="34830475-5483-4739-bce9-a964168a2eeb">
          <annotation></annotation>
          <assignFromContext>false</assignFromContext>
          <assignToContext>false</assignToContext>
          <inputType>STRING</inputType>
          <isList>false</isList>
          <required>false</required>
          <isPersisted>true</isPersisted>
          <inputSymbol>rowDelimiter</inputSymbol>
          <listDelimiter>,</listDelimiter>
          <value>|</value>
          <record>false</record>
        </staticBinding>
      </bindings>
      <transitions>
        <transition id="c52f0def-fbad-4d5c-9d27-5de81e16f913">
          <annotation>ec545f78-2e6b-454e-9b13-b1958628027b.c52f0def-fbad-4d5c-9d27-5de81e16f913.transition.description</annotation>
          <name>automation failure</name>
          <command>NEXT</command>
          <linkMode>false</linkMode>
          <responseSymbol>failure</responseSymbol>
          <shouldHandoff>false</shouldHandoff>
          <transitionValue>0.0</transitionValue>
          <destination>
            <refId>1fc81e06-e4fa-4441-96d5-3925647d161f</refId>
          </destination>
          <source>
            <refId>f995eb94-e0ee-4cc2-a2d9-9dc32206b56d</refId>
          </source>
          <positions>
            <point>
              <x>91.0</x>
              <y>68.0</y>
            </point>
            <point>
              <x>80.0</x>
              <y>244.0</y>
            </point>
          </positions>
          <labelPosition>
            <x>333.0</x>
            <y>0.0</y>
          </labelPosition>
        </transition>
        <transition id="6bb5cf0a-81c6-4cfe-9f8f-b8d296e6ef13">
          <annotation>ec545f78-2e6b-454e-9b13-b1958628027b.6bb5cf0a-81c6-4cfe-9f8f-b8d296e6ef13.transition.description</annotation>
          <name>success</name>
          <command>NEXT</command>
          <linkMode>false</linkMode>
          <responseSymbol>success</responseSymbol>
          <shouldHandoff>false</shouldHandoff>
          <transitionValue>0.0</transitionValue>
          <destination>
            <refId>0f649cf7-5267-476f-8ad8-debb624e27ff</refId>
          </destination>
          <source>
            <refId>f995eb94-e0ee-4cc2-a2d9-9dc32206b56d</refId>
          </source>
          <positions>
            <point>
              <x>91.0</x>
              <y>68.0</y>
            </point>
            <point>
              <x>72.0</x>
              <y>408.0</y>
            </point>
          </positions>
          <labelPosition>
            <x>333.0</x>
            <y>0.0</y>
          </labelPosition>
        </transition>
      </transitions>
      <properties/>
      <opRef>
        <refId>d5bbfad7-a102-4a0b-865e-8bf9026a0332</refId>
      </opRef>
      <assignments>
        <flowVariableAssignment id="1ab20ee4-f05b-40e3-ac60-5946a891d165">
          <annotation></annotation>
          <name>assignment</name>
          <action>OVERWRITE</action>
          <assignmentTargetType>FLOW_VARIABLE</assignmentTargetType>
          <contextKey>rowCount</contextKey>
          <expression id="a17197f7-1923-43c5-9633-f29031461298">
            <annotation></annotation>
            <name>Result: rowCount</name>
            <fieldName>rowCount</fieldName>
            <sourceType>AVAILABLE_RESULT</sourceType>
            <filters/>
          </expression>
        </flowVariableAssignment>
        <flowVariableAssignment id="1324320d-e60c-44a2-8970-b246ea63def9">
          <annotation></annotation>
          <name>assignment</name>
          <action>OVERWRITE</action>
          <assignmentTargetType>FLOW_VARIABLE</assignmentTargetType>
          <contextKey>columnNames</contextKey>
          <expression id="ed3d7424-47e0-4eef-b0c0-a90e1b3984b9">
            <annotation></annotation>
            <name>Result: columnNames</name>
            <fieldName>columnNames</fieldName>
            <sourceType>AVAILABLE_RESULT</sourceType>
            <filters/>
          </expression>
        </flowVariableAssignment>
        <flowVariableAssignment id="554ac77f-4bea-4c75-b32f-c415fcc2f480">
          <annotation></annotation>
          <name>assignment</name>
          <action>OVERWRITE</action>
          <assignmentTargetType>FLOW_VARIABLE</assignmentTargetType>
          <contextKey>queryResult</contextKey>
          <expression id="5cfaca44-80eb-457c-a200-8e7561f93f91">
            <annotation></annotation>
            <name>Result: queryResult</name>
            <fieldName>queryResult</fieldName>
            <sourceType>AVAILABLE_RESULT</sourceType>
            <filters/>
          </expression>
        </flowVariableAssignment>
        <flowVariableAssignment id="80342e59-b3c6-4da2-9efd-47559d37c869">
          <annotation></annotation>
          <name>assignment</name>
          <action>OVERWRITE</action>
          <assignmentTargetType>FLOW_VARIABLE</assignmentTargetType>
          <contextKey>errorMessage</contextKey>
          <expression id="b45be633-7e50-4744-89f2-0d4c43459595">
            <annotation></annotation>
            <name>Result: errorMessage</name>
            <fieldName>errorMessage</fieldName>
            <sourceType>AVAILABLE_RESULT</sourceType>
            <filters/>
          </expression>
        </flowVariableAssignment>
      </assignments>
      <throttleSize>0</throttleSize>
    </step>
    <step id="d5138e93-e35d-440d-a46b-8ac729f53540">
      <annotation>ec545f78-2e6b-454e-9b13-b1958628027b.d5138e93-e35d-440d-a46b-8ac729f53540.description</annotation>
      <name>Set Flow Variables : Convert DB Result to flow variable</name>
      <bounds>
        <x>208.0</x>
        <y>34.0</y>
      </bounds>
      <layer>-1</layer>
      <hideInbound>false</hideInbound>
      <iconSpec id="81b9dc31-9063-4e5d-8e31-87aae7005c2c">
        <baseIcon>jar.png</baseIcon>
        <basePath>Others/</basePath>
        <readOnly>false</readOnly>
        <layers>
          <iconSpec id="9b606aac-d958-4bd8-b2dc-86a4357305b9">
            <baseIcon>edit.png</baseIcon>
            <basePath>Annotations/</basePath>
            <readOnly>false</readOnly>
            <layers/>
          </iconSpec>
        </layers>
      </iconSpec>
      <addResultToRunContext>false</addResultToRunContext>
      <isCriticalStep>false</isCriticalStep>
      <isNonBlocking>false</isNonBlocking>
      <isParallelStep>false</isParallelStep>
      <isSingleResponse>false</isSingleResponse>
      <recordInHistory>false</recordInHistory>
      <recordRawOutput>true</recordRawOutput>
      <recordPrimaryOutput>true</recordPrimaryOutput>
      <checkPointStep>true</checkPointStep>
      <historyCheckPointStep>true</historyCheckPointStep>
      <scriptResultStep>false</scriptResultStep>
      <userPrompt></userPrompt>
      <bindings>
        <staticBinding id="1880d720-0a0e-4130-879d-6ffadc13fad9">
          <annotation></annotation>
          <fromContextKey>columnNames</fromContextKey>
          <assignFromContext>true</assignFromContext>
          <assignToContext>false</assignToContext>
          <inputType>STRING</inputType>
          <isList>false</isList>
          <required>true</required>
          <isPersisted>true</isPersisted>
          <inputSymbol>keyNames</inputSymbol>
          <listDelimiter>,</listDelimiter>
          <value></value>
          <record>false</record>
        </staticBinding>
        <staticBinding id="f45942ff-6e09-4c37-9da2-46c07d127f41">
          <annotation></annotation>
          <fromContextKey>queryResult</fromContextKey>
          <assignFromContext>true</assignFromContext>
          <assignToContext>false</assignToContext>
          <inputType>STRING</inputType>
          <isList>false</isList>
          <required>true</required>
          <isPersisted>true</isPersisted>
          <inputSymbol>myValues</inputSymbol>
          <listDelimiter>,</listDelimiter>
          <value></value>
          <record>false</record>
        </staticBinding>
        <staticBinding id="b92237a7-e261-451f-83b6-95db1e531f50">
          <annotation></annotation>
          <fromContextKey>columnDelimiter</fromContextKey>
          <assignFromContext>true</assignFromContext>
          <assignToContext>false</assignToContext>
          <inputType>STRING</inputType>
          <isList>false</isList>
          <required>false</required>
          <isPersisted>true</isPersisted>
          <inputSymbol>delimiter</inputSymbol>
          <listDelimiter>,</listDelimiter>
          <record>false</record>
        </staticBinding>
      </bindings>
      <transitions>
        <transition id="e101bf4d-9084-4288-bcf1-49ca6e715ba1">
          <annotation>ec545f78-2e6b-454e-9b13-b1958628027b.e101bf4d-9084-4288-bcf1-49ca6e715ba1.transition.description</annotation>
          <name>success</name>
          <command>NEXT</command>
          <linkMode>false</linkMode>
          <responseSymbol>success</responseSymbol>
          <shouldHandoff>false</shouldHandoff>
          <transitionValue>0.0</transitionValue>
          <destination>
            <refId>b404aa62-1666-4ba6-add1-b64d6a4af42f</refId>
          </destination>
          <source>
            <refId>d5138e93-e35d-440d-a46b-8ac729f53540</refId>
          </source>
          <positions>
            <point>
              <x>258.0</x>
              <y>68.0</y>
            </point>
            <point>
              <x>680.0</x>
              <y>68.0</y>
            </point>
          </positions>
          <labelPosition>
            <x>333.0</x>
            <y>0.0</y>
          </labelPosition>
        </transition>
      </transitions>
      <properties/>
      <opRef>
        <refId>3a06f909-df15-40f6-b76d-62fd669ee5b4</refId>
      </opRef>
      <assignments/>
      <throttleSize>0</throttleSize>
    </step>
    <returnStep id="1fc81e06-e4fa-4441-96d5-3925647d161f">
      <annotation></annotation>
      <name>Error : failure</name>
      <bounds>
        <x>390.0</x>
        <y>260.0</y>
      </bounds>
      <layer>-1</layer>
      <hideInbound>false</hideInbound>
      <addResultToRunContext>false</addResultToRunContext>
      <isCriticalStep>false</isCriticalStep>
      <isNonBlocking>false</isNonBlocking>
      <isParallelStep>false</isParallelStep>
      <isSingleResponse>false</isSingleResponse>
      <recordInHistory>false</recordInHistory>
      <recordRawOutput>true</recordRawOutput>
      <recordPrimaryOutput>true</recordPrimaryOutput>
      <checkPointStep>true</checkPointStep>
      <historyCheckPointStep>true</historyCheckPointStep>
      <scriptResultStep>false</scriptResultStep>
      <userPrompt></userPrompt>
      <bindings>
        <staticBinding id="20e2a342-d3e2-4c60-9f3d-767011c216f9">
          <annotation></annotation>
          <assignFromContext>true</assignFromContext>
          <assignToContext>false</assignToContext>
          <inputType>STRING</inputType>
          <isList>false</isList>
          <required>false</required>
          <isPersisted>true</isPersisted>
          <inputSymbol>errorMessage</inputSymbol>
          <listDelimiter>,</listDelimiter>
          <value>An error occured in step &quot;Determine Update Screens&quot;</value>
          <record>false</record>
        </staticBinding>
        <staticBinding id="12fd2f69-e31c-4268-b322-ab4984c430f9">
          <annotation></annotation>
          <assignFromContext>false</assignFromContext>
          <assignToContext>false</assignToContext>
          <inputType>STRING</inputType>
          <isList>false</isList>
          <required>false</required>
          <isPersisted>true</isPersisted>
          <inputSymbol>failureFlag</inputSymbol>
          <listDelimiter>,</listDelimiter>
          <value>True</value>
          <record>false</record>
        </staticBinding>
      </bindings>
      <transitions>
        <transition id="899a8e04-b36e-4e0d-b220-728da0cc581f">
          <annotation></annotation>
          <name>return</name>
          <command>NEXT</command>
          <linkMode>false</linkMode>
          <responseSymbol>failure</responseSymbol>
          <shouldHandoff>false</shouldHandoff>
          <transitionValue>0.0</transitionValue>
          <destination>
            <refId>1fc81e06-e4fa-4441-96d5-3925647d161f</refId>
          </destination>
          <source>
            <refId>1fc81e06-e4fa-4441-96d5-3925647d161f</refId>
          </source>
          <positions/>
        </transition>
      </transitions>
      <properties/>
      <returnStepType>ERROR</returnStepType>
      <assignments>
        <flowVariableAssignment id="ad2b9dff-4031-4313-acdb-a64ece803a85">
          <annotation></annotation>
          <name>assignment</name>
          <action>OVERWRITE</action>
          <assignmentTargetType>FLOW_OUTPUT_FIELD</assignmentTargetType>
          <contextKey>failureFlag</contextKey>
          <expression id="4f0b9253-55f8-4038-aa9c-5f4df285251b">
            <annotation></annotation>
            <name>Input: failureFlag</name>
            <fieldName>failureFlag</fieldName>
            <sourceType>INPUT</sourceType>
            <filters/>
          </expression>
        </flowVariableAssignment>
        <flowVariableAssignment id="fe3c7548-c2d9-468b-a3f7-95ca0ecca5a6">
          <annotation></annotation>
          <name>assignment</name>
          <action>OVERWRITE</action>
          <assignmentTargetType>FLOW_OUTPUT_FIELD</assignmentTargetType>
          <contextKey>errorMessage</contextKey>
          <expression id="078c1874-c067-4216-b3c6-6ab025090abb">
            <annotation></annotation>
            <name>Input: errorMessage</name>
            <fieldName>errorMessage</fieldName>
            <sourceType>INPUT</sourceType>
            <filters/>
          </expression>
        </flowVariableAssignment>
      </assignments>
    </returnStep>
    <step id="b404aa62-1666-4ba6-add1-b64d6a4af42f">
      <annotation>ec545f78-2e6b-454e-9b13-b1958628027b.b404aa62-1666-4ba6-add1-b64d6a4af42f.description</annotation>
      <name>Compare Flags</name>
      <bounds>
        <x>390.0</x>
        <y>34.0</y>
      </bounds>
      <layer>-1</layer>
      <hideInbound>false</hideInbound>
      <iconSpec id="11fd8661-c18e-40b7-8cd6-4eb11c2ab9f6">
        <baseIcon>display_report.png</baseIcon>
        <basePath>Utilities/</basePath>
        <readOnly>false</readOnly>
        <layers/>
      </iconSpec>
      <addResultToRunContext>false</addResultToRunContext>
      <isCriticalStep>false</isCriticalStep>
      <isNonBlocking>false</isNonBlocking>
      <isParallelStep>false</isParallelStep>
      <isSingleResponse>false</isSingleResponse>
      <recordInHistory>false</recordInHistory>
      <recordRawOutput>true</recordRawOutput>
      <recordPrimaryOutput>true</recordPrimaryOutput>
      <checkPointStep>true</checkPointStep>
      <historyCheckPointStep>true</historyCheckPointStep>
      <scriptResultStep>false</scriptResultStep>
      <userPrompt></userPrompt>
      <scriptlet id="4a8696ee-990f-42f4-9740-d40dc881ff5f">
        <annotation></annotation>
        <name>Step Compare Flags in Flow Determine Update Screens (b404aa62-1666-4ba6-add1-b64d6a4af42f)</name>
        <script>try{
	variableNamesList = variableNames.split(delimiter);	
	for (var i = 0; i &lt; variableNamesList.length; i++) {		 				
		scriptletContext.put(
			variableNamesList[i] + &apos;Flag&apos;,
			scriptletContext.get(variableNamesList[i]).trim() == &apos;Y&apos; ? &apos;True&apos; : &apos;False&apos;
		);
	}	
	response = &quot;success&quot;;
} catch(err) {
	errorMessage = &apos;An error occured while comparing screen flags : &apos; + err.message;
	scriptletContext.put(&quot;errorMessage&quot;, errorMessage);	
	response = &quot;failure&quot;;
}
scriptletResponse = response</script>
        <type>NASHORN</type>
      </scriptlet>
      <bindings>
        <staticBinding id="4cd37e7b-3fe5-42aa-8f5f-eb4df38123cb">
          <annotation></annotation>
          <fromContextKey>columnNames</fromContextKey>
          <assignFromContext>true</assignFromContext>
          <assignToContext>false</assignToContext>
          <inputType>STRING</inputType>
          <isList>false</isList>
          <required>false</required>
          <isPersisted>true</isPersisted>
          <inputSymbol>variableNames</inputSymbol>
          <listDelimiter>,</listDelimiter>
          <value></value>
          <record>false</record>
        </staticBinding>
        <staticBinding id="6bdb26d9-316d-4297-b675-ea15abde0249">
          <annotation></annotation>
          <fromContextKey>columnDelimiter</fromContextKey>
          <assignFromContext>true</assignFromContext>
          <assignToContext>false</assignToContext>
          <inputType>STRING</inputType>
          <isList>false</isList>
          <required>false</required>
          <isPersisted>true</isPersisted>
          <inputSymbol>delimiter</inputSymbol>
          <listDelimiter>,</listDelimiter>
          <value></value>
          <record>false</record>
        </staticBinding>
      </bindings>
      <transitions>
        <transition id="13c1ff90-d531-4f9c-be67-45915b51b252">
          <annotation>ec545f78-2e6b-454e-9b13-b1958628027b.13c1ff90-d531-4f9c-be67-45915b51b252.transition.description</annotation>
          <name>automation failure</name>
          <command>NEXT</command>
          <linkMode>false</linkMode>
          <responseSymbol>failure</responseSymbol>
          <shouldHandoff>false</shouldHandoff>
          <transitionValue>0.0</transitionValue>
          <destination>
            <refId>1fc81e06-e4fa-4441-96d5-3925647d161f</refId>
          </destination>
          <source>
            <refId>b404aa62-1666-4ba6-add1-b64d6a4af42f</refId>
          </source>
          <positions>
            <point>
              <x>260.0</x>
              <y>364.0</y>
            </point>
            <point>
              <x>80.0</x>
              <y>214.0</y>
            </point>
          </positions>
          <labelPosition>
            <x>333.0</x>
            <y>0.0</y>
          </labelPosition>
        </transition>
        <transition id="c2b5345a-8fa8-408d-b793-06226bce97fe">
          <annotation></annotation>
          <name>success</name>
          <command>NEXT</command>
          <linkMode>false</linkMode>
          <responseSymbol>success</responseSymbol>
          <shouldHandoff>false</shouldHandoff>
          <transitionValue>0.0</transitionValue>
          <destination>
            <refId>3edbce51-839e-480c-8a63-359eb227c3f0</refId>
          </destination>
          <source>
            <refId>b404aa62-1666-4ba6-add1-b64d6a4af42f</refId>
          </source>
          <positions>
            <point>
              <x>260.0</x>
              <y>364.0</y>
            </point>
            <point>
              <x>500.0</x>
              <y>334.0</y>
            </point>
          </positions>
          <labelPosition>
            <x>333.0</x>
            <y>0.0</y>
          </labelPosition>
        </transition>
      </transitions>
      <properties/>
      <opRef>
        <refId>e46b91b4-6637-4b3d-883a-e86436d9eb3a</refId>
      </opRef>
      <assignments/>
      <throttleSize>0</throttleSize>
    </step>
    <returnStep id="3edbce51-839e-480c-8a63-359eb227c3f0">
      <annotation></annotation>
      <name>Resolved : success</name>
      <bounds>
        <x>810.0</x>
        <y>34.0</y>
      </bounds>
      <layer>-1</layer>
      <hideInbound>false</hideInbound>
      <addResultToRunContext>false</addResultToRunContext>
      <isCriticalStep>false</isCriticalStep>
      <isNonBlocking>false</isNonBlocking>
      <isParallelStep>false</isParallelStep>
      <isSingleResponse>false</isSingleResponse>
      <recordInHistory>false</recordInHistory>
      <recordRawOutput>true</recordRawOutput>
      <recordPrimaryOutput>true</recordPrimaryOutput>
      <checkPointStep>true</checkPointStep>
      <historyCheckPointStep>true</historyCheckPointStep>
      <scriptResultStep>false</scriptResultStep>
      <userPrompt></userPrompt>
      <bindings>
        <staticBinding id="daa9dd6d-0959-4f51-930c-5aeb9200aac5">
          <annotation></annotation>
          <assignFromContext>true</assignFromContext>
          <assignToContext>false</assignToContext>
          <inputType>STRING</inputType>
          <isList>false</isList>
          <required>false</required>
          <isPersisted>true</isPersisted>
          <inputSymbol>updatePDSWFlag</inputSymbol>
          <listDelimiter>,</listDelimiter>
          <value></value>
          <record>false</record>
        </staticBinding>
        <staticBinding id="4f521a66-79df-47ca-b6cb-e4eb696ed023">
          <annotation></annotation>
          <assignFromContext>true</assignFromContext>
          <assignToContext>false</assignToContext>
          <inputType>STRING</inputType>
          <isList>false</isList>
          <required>false</required>
          <isPersisted>true</isPersisted>
          <inputSymbol>updateFACTFlag</inputSymbol>
          <listDelimiter>,</listDelimiter>
          <value></value>
          <record>false</record>
        </staticBinding>
        <staticBinding id="90b8f94c-14f8-4ef6-a405-f4bd53968dd7">
          <annotation></annotation>
          <assignFromContext>true</assignFromContext>
          <assignToContext>false</assignToContext>
          <inputType>STRING</inputType>
          <isList>false</isList>
          <required>false</required>
          <isPersisted>true</isPersisted>
          <inputSymbol>updateCS90Flag</inputSymbol>
          <listDelimiter>,</listDelimiter>
          <value></value>
          <record>false</record>
        </staticBinding>
        <staticBinding id="a507220c-169e-49d7-a740-d9c42c5c0a33">
          <annotation></annotation>
          <assignFromContext>true</assignFromContext>
          <assignToContext>false</assignToContext>
          <inputType>STRING</inputType>
          <isList>false</isList>
          <required>false</required>
          <isPersisted>true</isPersisted>
          <inputSymbol>updateLBRDFlag</inputSymbol>
          <listDelimiter>,</listDelimiter>
          <value></value>
          <record>false</record>
        </staticBinding>
        <staticBinding id="143fdb6e-777c-43ac-998b-806abd9a717d">
          <annotation></annotation>
          <assignFromContext>true</assignFromContext>
          <assignToContext>false</assignToContext>
          <inputType>STRING</inputType>
          <isList>false</isList>
          <required>false</required>
          <isPersisted>true</isPersisted>
          <inputSymbol>updateCCTPFlag</inputSymbol>
          <listDelimiter>,</listDelimiter>
          <value></value>
          <record>false</record>
        </staticBinding>
        <staticBinding id="ceaa208a-f360-4672-a43c-53f138cd0c6e">
          <annotation></annotation>
          <assignFromContext>true</assignFromContext>
          <assignToContext>false</assignToContext>
          <inputType>STRING</inputType>
          <isList>false</isList>
          <required>false</required>
          <isPersisted>true</isPersisted>
          <inputSymbol>updateVCHGFlag</inputSymbol>
          <listDelimiter>,</listDelimiter>
          <value></value>
          <record>false</record>
        </staticBinding>
        <staticBinding id="1bc779a4-e6ec-4d23-9eb0-b02876b7641f">
          <annotation></annotation>
          <assignFromContext>true</assignFromContext>
          <assignToContext>false</assignToContext>
          <inputType>STRING</inputType>
          <isList>false</isList>
          <required>false</required>
          <isPersisted>true</isPersisted>
          <inputSymbol>updateLNS4Flag</inputSymbol>
          <listDelimiter>,</listDelimiter>
          <value></value>
          <record>false</record>
        </staticBinding>
        <staticBinding id="32ea7606-b8d6-48c2-92ad-3a3ba5e474b0">
          <annotation></annotation>
          <assignFromContext>true</assignFromContext>
          <assignToContext>false</assignToContext>
          <inputType>STRING</inputType>
          <isList>false</isList>
          <required>false</required>
          <isPersisted>true</isPersisted>
          <inputSymbol>updateVRMIFlag</inputSymbol>
          <listDelimiter>,</listDelimiter>
          <value></value>
          <record>false</record>
        </staticBinding>
        <staticBinding id="c4a61f06-7e37-48c0-8230-fab6a1d1813c">
          <annotation></annotation>
          <assignFromContext>true</assignFromContext>
          <assignToContext>false</assignToContext>
          <inputType>STRING</inputType>
          <isList>false</isList>
          <required>false</required>
          <isPersisted>true</isPersisted>
          <inputSymbol>updateDATEFlag</inputSymbol>
          <listDelimiter>,</listDelimiter>
          <value></value>
          <record>false</record>
        </staticBinding>
        <staticBinding id="310a11e2-1462-4000-88d2-084db9444c4c">
          <annotation></annotation>
          <assignFromContext>true</assignFromContext>
          <assignToContext>false</assignToContext>
          <inputType>STRING</inputType>
          <isList>false</isList>
          <required>false</required>
          <isPersisted>true</isPersisted>
          <inputSymbol>updateFADSFlag</inputSymbol>
          <listDelimiter>,</listDelimiter>
          <value></value>
          <record>false</record>
        </staticBinding>
        <staticBinding id="40427c86-ee44-462c-9f72-2a807f95a2de">
          <annotation></annotation>
          <assignFromContext>true</assignFromContext>
          <assignToContext>false</assignToContext>
          <inputType>STRING</inputType>
          <isList>false</isList>
          <required>false</required>
          <isPersisted>true</isPersisted>
          <inputSymbol>updateTENTFlag</inputSymbol>
          <listDelimiter>,</listDelimiter>
          <value></value>
          <record>false</record>
        </staticBinding>
        <staticBinding id="9f3bc0fb-9b33-433a-9f03-35c7a8d222dc">
          <annotation></annotation>
          <assignFromContext>true</assignFromContext>
          <assignToContext>false</assignToContext>
          <inputType>STRING</inputType>
          <isList>false</isList>
          <required>false</required>
          <isPersisted>true</isPersisted>
          <inputSymbol>updatePRCDFlag</inputSymbol>
          <listDelimiter>,</listDelimiter>
          <value></value>
          <record>false</record>
        </staticBinding>
        <staticBinding id="06421e19-e1d1-46b6-9f37-d2c63300305d">
          <annotation></annotation>
          <assignFromContext>true</assignFromContext>
          <assignToContext>false</assignToContext>
          <inputType>STRING</inputType>
          <isList>false</isList>
          <required>false</required>
          <isPersisted>true</isPersisted>
          <inputSymbol>updateDRDBFlag</inputSymbol>
          <listDelimiter>,</listDelimiter>
          <value></value>
          <record>false</record>
        </staticBinding>
        <staticBinding id="b356af77-ccd8-4162-bda3-87311d1fb5f1">
          <annotation></annotation>
          <assignFromContext>true</assignFromContext>
          <assignToContext>false</assignToContext>
          <inputType>STRING</inputType>
          <isList>false</isList>
          <required>false</required>
          <isPersisted>true</isPersisted>
          <inputSymbol>updateVMGDFlag</inputSymbol>
          <listDelimiter>,</listDelimiter>
          <value></value>
          <record>false</record>
        </staticBinding>
        <staticBinding id="6249481d-ec03-4813-835a-76eb1510ec40">
          <annotation></annotation>
          <assignFromContext>true</assignFromContext>
          <assignToContext>false</assignToContext>
          <inputType>STRING</inputType>
          <isList>false</isList>
          <required>false</required>
          <isPersisted>true</isPersisted>
          <inputSymbol>updateACHCFlag</inputSymbol>
          <listDelimiter>,</listDelimiter>
          <value></value>
          <record>false</record>
        </staticBinding>
      </bindings>
      <transitions>
        <transition id="6f138f96-7c1b-4fc6-b68f-6d83f20d77e2">
          <annotation></annotation>
          <name>return</name>
          <command>NEXT</command>
          <linkMode>false</linkMode>
          <responseSymbol>success</responseSymbol>
          <shouldHandoff>false</shouldHandoff>
          <transitionValue>0.0</transitionValue>
          <destination>
            <refId>3edbce51-839e-480c-8a63-359eb227c3f0</refId>
          </destination>
          <source>
            <refId>3edbce51-839e-480c-8a63-359eb227c3f0</refId>
          </source>
          <positions/>
        </transition>
      </transitions>
      <properties/>
      <returnStepType>RESOLVED</returnStepType>
      <assignments>
        <flowVariableAssignment id="21cd4219-0d21-402f-b211-50025684c3c3">
          <annotation></annotation>
          <name>assignment</name>
          <action>OVERWRITE</action>
          <assignmentTargetType>FLOW_OUTPUT_FIELD</assignmentTargetType>
          <contextKey>updateACHCFlag</contextKey>
          <expression id="b7e908da-abe9-478f-8a6e-c39293e0765a">
            <annotation></annotation>
            <name>Input: updateACHCFlag</name>
            <fieldName>updateACHCFlag</fieldName>
            <sourceType>INPUT</sourceType>
            <filters/>
          </expression>
        </flowVariableAssignment>
        <flowVariableAssignment id="b4513c1d-4c35-4c5b-b33a-f12ccfd4470b">
          <annotation></annotation>
          <name>assignment</name>
          <action>OVERWRITE</action>
          <assignmentTargetType>FLOW_OUTPUT_FIELD</assignmentTargetType>
          <contextKey>updateVMGDFlag</contextKey>
          <expression id="ff3dbb1d-b198-4681-b577-483ea12c7001">
            <annotation></annotation>
            <name>Input: updateVMGDFlag</name>
            <fieldName>updateVMGDFlag</fieldName>
            <sourceType>INPUT</sourceType>
            <filters/>
          </expression>
        </flowVariableAssignment>
        <flowVariableAssignment id="19c08e59-2adb-41c8-bb8d-e313d8aba6b8">
          <annotation></annotation>
          <name>assignment</name>
          <action>OVERWRITE</action>
          <assignmentTargetType>FLOW_OUTPUT_FIELD</assignmentTargetType>
          <contextKey>updateDRDBFlag</contextKey>
          <expression id="fbd7f97d-bb59-43e0-9ff2-f6ec6711f843">
            <annotation></annotation>
            <name>Input: updateDRDBFlag</name>
            <fieldName>updateDRDBFlag</fieldName>
            <sourceType>INPUT</sourceType>
            <filters/>
          </expression>
        </flowVariableAssignment>
        <flowVariableAssignment id="df0dde78-1743-493f-b476-738bb1a90959">
          <annotation></annotation>
          <name>assignment</name>
          <action>OVERWRITE</action>
          <assignmentTargetType>FLOW_OUTPUT_FIELD</assignmentTargetType>
          <contextKey>updatePRCDFlag</contextKey>
          <expression id="64131ede-6828-4951-83bc-99d2ed81b44e">
            <annotation></annotation>
            <name>Input: updatePRCDFlag</name>
            <fieldName>updatePRCDFlag</fieldName>
            <sourceType>INPUT</sourceType>
            <filters/>
          </expression>
        </flowVariableAssignment>
        <flowVariableAssignment id="9b6d5e4b-6f4b-408e-b2be-98be7e78aa99">
          <annotation></annotation>
          <name>assignment</name>
          <action>OVERWRITE</action>
          <assignmentTargetType>FLOW_OUTPUT_FIELD</assignmentTargetType>
          <contextKey>updateTENTFlag</contextKey>
          <expression id="b9a81886-ee87-4824-abc1-a3569e07430b">
            <annotation></annotation>
            <name>Input: updateTENTFlag</name>
            <fieldName>updateTENTFlag</fieldName>
            <sourceType>INPUT</sourceType>
            <filters/>
          </expression>
        </flowVariableAssignment>
        <flowVariableAssignment id="a29579ce-95f6-4b7f-b534-d5261c16ed0a">
          <annotation></annotation>
          <name>assignment</name>
          <action>OVERWRITE</action>
          <assignmentTargetType>FLOW_OUTPUT_FIELD</assignmentTargetType>
          <contextKey>updateFADSFlag</contextKey>
          <expression id="bf624e25-5e3c-4290-9ec3-2736aee803ee">
            <annotation></annotation>
            <name>Input: updateFADSFlag</name>
            <fieldName>updateFADSFlag</fieldName>
            <sourceType>INPUT</sourceType>
            <filters/>
          </expression>
        </flowVariableAssignment>
        <flowVariableAssignment id="db2dd155-d9c1-4728-bc0b-4d5a1b1d53a8">
          <annotation></annotation>
          <name>assignment</name>
          <action>OVERWRITE</action>
          <assignmentTargetType>FLOW_OUTPUT_FIELD</assignmentTargetType>
          <contextKey>updateDATEFlag</contextKey>
          <expression id="898121b5-1c60-4bf9-99b2-f72c2d94e619">
            <annotation></annotation>
            <name>Input: updateDATEFlag</name>
            <fieldName>updateDATEFlag</fieldName>
            <sourceType>INPUT</sourceType>
            <filters/>
          </expression>
        </flowVariableAssignment>
        <flowVariableAssignment id="0f4543df-e30e-4af9-925f-5a81a3c328f2">
          <annotation></annotation>
          <name>assignment</name>
          <action>OVERWRITE</action>
          <assignmentTargetType>FLOW_OUTPUT_FIELD</assignmentTargetType>
          <contextKey>updateVRMIFlag</contextKey>
          <expression id="90ef225c-935b-4d20-be1a-622e25c0886c">
            <annotation></annotation>
            <name>Input: updateVRMIFlag</name>
            <fieldName>updateVRMIFlag</fieldName>
            <sourceType>INPUT</sourceType>
            <filters/>
          </expression>
        </flowVariableAssignment>
        <flowVariableAssignment id="55d98dc8-efea-4246-aee6-0b29befa4a9d">
          <annotation></annotation>
          <name>assignment</name>
          <action>OVERWRITE</action>
          <assignmentTargetType>FLOW_OUTPUT_FIELD</assignmentTargetType>
          <contextKey>updateLNS4Flag</contextKey>
          <expression id="67995d5c-10e5-47d2-970e-113cd986518e">
            <annotation></annotation>
            <name>Input: updateLNS4Flag</name>
            <fieldName>updateLNS4Flag</fieldName>
            <sourceType>INPUT</sourceType>
            <filters/>
          </expression>
        </flowVariableAssignment>
        <flowVariableAssignment id="31e3eb99-3a05-4759-a3bb-6c2a792571ab">
          <annotation></annotation>
          <name>assignment</name>
          <action>OVERWRITE</action>
          <assignmentTargetType>FLOW_OUTPUT_FIELD</assignmentTargetType>
          <contextKey>updateVCHGFlag</contextKey>
          <expression id="7385b5e1-153f-41ed-beb6-d235092bf3b7">
            <annotation></annotation>
            <name>Input: updateVCHGFlag</name>
            <fieldName>updateVCHGFlag</fieldName>
            <sourceType>INPUT</sourceType>
            <filters/>
          </expression>
        </flowVariableAssignment>
        <flowVariableAssignment id="cec95de3-9997-465a-87fb-ee92e9ff06d7">
          <annotation></annotation>
          <name>assignment</name>
          <action>OVERWRITE</action>
          <assignmentTargetType>FLOW_OUTPUT_FIELD</assignmentTargetType>
          <contextKey>updateCCTPFlag</contextKey>
          <expression id="5626fb9e-3a94-4a2f-b218-7c817f11b6ac">
            <annotation></annotation>
            <name>Input: updateCCTPFlag</name>
            <fieldName>updateCCTPFlag</fieldName>
            <sourceType>INPUT</sourceType>
            <filters/>
          </expression>
        </flowVariableAssignment>
        <flowVariableAssignment id="ef03e3e5-cce7-4676-910c-b024a10b5276">
          <annotation></annotation>
          <name>assignment</name>
          <action>OVERWRITE</action>
          <assignmentTargetType>FLOW_OUTPUT_FIELD</assignmentTargetType>
          <contextKey>updateLBRDFlag</contextKey>
          <expression id="d1dc50b6-4997-4851-829a-7b7424dd9cd8">
            <annotation></annotation>
            <name>Input: updateLBRDFlag</name>
            <fieldName>updateLBRDFlag</fieldName>
            <sourceType>INPUT</sourceType>
            <filters/>
          </expression>
        </flowVariableAssignment>
        <flowVariableAssignment id="405b9c68-0244-479d-a6da-90ce45b0c222">
          <annotation></annotation>
          <name>assignment</name>
          <action>OVERWRITE</action>
          <assignmentTargetType>FLOW_OUTPUT_FIELD</assignmentTargetType>
          <contextKey>updateCS90Flag</contextKey>
          <expression id="4833e5ba-4f29-4020-8420-f2dbab63bb60">
            <annotation></annotation>
            <name>Input: updateCS90Flag</name>
            <fieldName>updateCS90Flag</fieldName>
            <sourceType>INPUT</sourceType>
            <filters/>
          </expression>
        </flowVariableAssignment>
        <flowVariableAssignment id="3cb2de73-4ce6-437f-858a-8b6c0dffa58a">
          <annotation></annotation>
          <name>assignment</name>
          <action>OVERWRITE</action>
          <assignmentTargetType>FLOW_OUTPUT_FIELD</assignmentTargetType>
          <contextKey>updateFACTFlag</contextKey>
          <expression id="cc878123-7b23-48dd-95ac-98a62d9a703d">
            <annotation></annotation>
            <name>Input: updateFACTFlag</name>
            <fieldName>updateFACTFlag</fieldName>
            <sourceType>INPUT</sourceType>
            <filters/>
          </expression>
        </flowVariableAssignment>
        <flowVariableAssignment id="5df554ba-3846-42f9-99b1-c0c85e8c0eda">
          <annotation></annotation>
          <name>assignment</name>
          <action>OVERWRITE</action>
          <assignmentTargetType>FLOW_OUTPUT_FIELD</assignmentTargetType>
          <contextKey>updatePDSWFlag</contextKey>
          <expression id="02668677-63e5-4bea-90df-5b0b76600db8">
            <annotation></annotation>
            <name>Input: updatePDSWFlag</name>
            <fieldName>updatePDSWFlag</fieldName>
            <sourceType>INPUT</sourceType>
            <filters/>
          </expression>
        </flowVariableAssignment>
      </assignments>
    </returnStep>
    <step id="0f649cf7-5267-476f-8ad8-debb624e27ff">
      <annotation>ec545f78-2e6b-454e-9b13-b1958628027b.0f649cf7-5267-476f-8ad8-debb624e27ff.description</annotation>
      <name>Check Row Count ==1?</name>
      <bounds>
        <x>30.0</x>
        <y>30.0</y>
      </bounds>
      <layer>-1</layer>
      <hideInbound>false</hideInbound>
      <addResultToRunContext>false</addResultToRunContext>
      <isCriticalStep>false</isCriticalStep>
      <isNonBlocking>false</isNonBlocking>
      <isParallelStep>false</isParallelStep>
      <isSingleResponse>false</isSingleResponse>
      <recordInHistory>false</recordInHistory>
      <recordRawOutput>true</recordRawOutput>
      <recordPrimaryOutput>true</recordPrimaryOutput>
      <checkPointStep>true</checkPointStep>
      <historyCheckPointStep>true</historyCheckPointStep>
      <scriptResultStep>false</scriptResultStep>
      <userPrompt></userPrompt>
      <bindings>
        <staticBinding id="3ffeb1ad-283f-44f1-a096-cf4342a588b0">
          <annotation></annotation>
          <fromContextKey>rowCount</fromContextKey>
          <assignFromContext>true</assignFromContext>
          <assignToContext>false</assignToContext>
          <inputType>STRING</inputType>
          <isList>false</isList>
          <required>true</required>
          <isPersisted>true</isPersisted>
          <inputSymbol>value1</inputSymbol>
          <listDelimiter>,</listDelimiter>
          <value></value>
          <record>false</record>
        </staticBinding>
        <staticBinding id="cd81cd82-6660-43c8-80da-b83ef5025735">
          <annotation></annotation>
          <assignFromContext>false</assignFromContext>
          <assignToContext>false</assignToContext>
          <inputType>STRING</inputType>
          <isList>false</isList>
          <required>true</required>
          <isPersisted>true</isPersisted>
          <inputSymbol>value2</inputSymbol>
          <listDelimiter>,</listDelimiter>
          <value>1</value>
          <record>false</record>
        </staticBinding>
        <staticBinding id="cf7b3859-4821-49cc-abc2-de7ec3ba74f8">
          <annotation></annotation>
          <toContextKey></toContextKey>
          <fromContextKey></fromContextKey>
          <assignFromContext>false</assignFromContext>
          <assignToContext>false</assignToContext>
          <inputType>STRING</inputType>
          <recordKey></recordKey>
          <isList>false</isList>
          <required>false</required>
          <isPersisted>true</isPersisted>
          <inputSymbol>operation</inputSymbol>
          <listDelimiter></listDelimiter>
          <value>==</value>
          <record>false</record>
        </staticBinding>
      </bindings>
      <transitions>
        <transition id="081838ee-dc0f-416d-b22b-1a25bafd1d72">
          <annotation>ec545f78-2e6b-454e-9b13-b1958628027b.081838ee-dc0f-416d-b22b-1a25bafd1d72.transition.description</annotation>
          <name>rowcount == 1</name>
          <command>NEXT</command>
          <linkMode>false</linkMode>
          <responseSymbol>success</responseSymbol>
          <shouldHandoff>false</shouldHandoff>
          <transitionValue>0.0</transitionValue>
          <destination>
            <refId>d5138e93-e35d-440d-a46b-8ac729f53540</refId>
          </destination>
          <source>
            <refId>0f649cf7-5267-476f-8ad8-debb624e27ff</refId>
          </source>
          <positions>
            <point>
              <x>72.0</x>
              <y>408.0</y>
            </point>
            <point>
              <x>258.0</x>
              <y>68.0</y>
            </point>
          </positions>
          <labelPosition>
            <x>333.0</x>
            <y>0.0</y>
          </labelPosition>
        </transition>
        <transition id="02735f3f-b09b-4142-9258-1e0a272667f6">
          <annotation>ec545f78-2e6b-454e-9b13-b1958628027b.02735f3f-b09b-4142-9258-1e0a272667f6.transition.description</annotation>
          <name>rowcount != 1</name>
          <command>NEXT</command>
          <linkMode>false</linkMode>
          <responseSymbol>failure</responseSymbol>
          <shouldHandoff>false</shouldHandoff>
          <transitionValue>0.0</transitionValue>
          <destination>
            <refId>7a9cfd94-d98f-4d1d-80de-d807ca7b2abf</refId>
          </destination>
          <source>
            <refId>0f649cf7-5267-476f-8ad8-debb624e27ff</refId>
          </source>
          <positions>
            <point>
              <x>72.0</x>
              <y>408.0</y>
            </point>
            <point>
              <x>260.0</x>
              <y>424.0</y>
            </point>
          </positions>
          <labelPosition>
            <x>333.0</x>
            <y>0.0</y>
          </labelPosition>
        </transition>
      </transitions>
      <properties/>
      <opRef>
        <refId>6c87ce31-0fc7-40c6-9673-ecd1f8eba999</refId>
      </opRef>
      <assignments/>
      <throttleSize>0</throttleSize>
    </step>
    <step id="7a9cfd94-d98f-4d1d-80de-d807ca7b2abf">
      <annotation>ec545f78-2e6b-454e-9b13-b1958628027b.7a9cfd94-d98f-4d1d-80de-d807ca7b2abf.description</annotation>
      <name>Set Error Message</name>
      <bounds>
        <x>208.0</x>
        <y>164.0</y>
      </bounds>
      <layer>-1</layer>
      <hideInbound>false</hideInbound>
      <addResultToRunContext>false</addResultToRunContext>
      <isCriticalStep>false</isCriticalStep>
      <isNonBlocking>false</isNonBlocking>
      <isParallelStep>false</isParallelStep>
      <isSingleResponse>false</isSingleResponse>
      <recordInHistory>false</recordInHistory>
      <recordRawOutput>true</recordRawOutput>
      <recordPrimaryOutput>true</recordPrimaryOutput>
      <checkPointStep>true</checkPointStep>
      <historyCheckPointStep>true</historyCheckPointStep>
      <scriptResultStep>false</scriptResultStep>
      <userPrompt></userPrompt>
      <bindings>
        <staticBinding id="9a217521-6bf7-429d-80a9-131d7faebc99">
          <annotation></annotation>
          <assignFromContext>false</assignFromContext>
          <assignToContext>false</assignToContext>
          <inputType>STRING</inputType>
          <isList>false</isList>
          <required>true</required>
          <isPersisted>true</isPersisted>
          <inputSymbol>keyName</inputSymbol>
          <listDelimiter>,</listDelimiter>
          <value>errorMessage</value>
          <record>false</record>
        </staticBinding>
        <staticBinding id="f8bcacf5-a5da-4076-890f-9fd1ecef9431">
          <annotation></annotation>
          <assignFromContext>false</assignFromContext>
          <assignToContext>false</assignToContext>
          <inputType>STRING</inputType>
          <isList>false</isList>
          <required>true</required>
          <isPersisted>true</isPersisted>
          <inputSymbol>myValue</inputSymbol>
          <listDelimiter>,</listDelimiter>
          <value>An error occured in step &quot;Determine Update Screens&quot; : number of rows retured is not equaled to 1</value>
          <record>false</record>
        </staticBinding>
      </bindings>
      <transitions>
        <transition id="80e1daa6-48d0-43f9-b1e0-3deb0249a567">
          <annotation></annotation>
          <name>success</name>
          <command>NEXT</command>
          <linkMode>false</linkMode>
          <responseSymbol>success</responseSymbol>
          <shouldHandoff>false</shouldHandoff>
          <transitionValue>0.0</transitionValue>
          <destination>
            <refId>1fc81e06-e4fa-4441-96d5-3925647d161f</refId>
          </destination>
          <source>
            <refId>7a9cfd94-d98f-4d1d-80de-d807ca7b2abf</refId>
          </source>
          <positions>
            <point>
              <x>260.0</x>
              <y>424.0</y>
            </point>
            <point>
              <x>440.0</x>
              <y>244.0</y>
            </point>
          </positions>
          <labelPosition>
            <x>333.0</x>
            <y>0.0</y>
          </labelPosition>
        </transition>
      </transitions>
      <properties/>
      <opRef>
        <refId>f3112e9d-ed88-47bf-be86-2f99e8541a33</refId>
      </opRef>
      <assignments/>
      <throttleSize>0</throttleSize>
    </step>
  </steps>
  <startSteps>f995eb94-e0ee-4cc2-a2d9-9dc32206b56d</startSteps>
</flow>